partitiontypes/Controller.py
partitiontypes/PartitionTypes.py
partitiontypes/__init__.py
partitiontypes/__main__.py
partitiontypes/data/__init__.py
partitiontypes/data/partitiontypes.json
partitiontypes/util/Crawler.py
partitiontypes/util/PartitionId.py
partitiontypes/util/__init__.py
partitiontypes-1.0.1.dist-info/LICENSE.md
partitiontypes-1.0.1.dist-info/METADATA
partitiontypes-1.0.1.dist-info/WHEEL
partitiontypes-1.0.1.dist-info/entry_points.txt
partitiontypes-1.0.1.dist-info/top_level.txt
partitiontypes-1.0.1.dist-info/RECORD
