Metadata-Version: 2.1
Name: partitiontypes
Version: 1.0.1
Summary: Provides values to identify the partition type within a master boot record
Home-page: https://github.com/5f0ne/partitiontypes
Author: 5f0
License: MIT
Classifier: Operating System :: OS Independent 
Classifier: Programming Language :: Python :: 3 
Classifier: License :: OSI Approved :: MIT License 
License-File: LICENSE.md
Requires-Dist: requests
